telepost/__init__.py
telepost-0.0.26.dist-info/LICENSE
telepost-0.0.26.dist-info/METADATA
telepost-0.0.26.dist-info/WHEEL
telepost-0.0.26.dist-info/top_level.txt
telepost-0.0.26.dist-info/RECORD
