Metadata-Version: 2.1
Name: telepost
Version: 0.0.26
Summary: Get post from telegram and make ready to repost it to other places (twitter / douban / reddit).
Home-page: https://github.com/gaoyunzhi/telepost
Author: Yunzhi Gao
Author-email: gaoyunzhi@gmail.com
License: UNKNOWN
Platform: UNKNOWN
Classifier: Programming Language :: Python :: 3
Classifier: License :: OSI Approved :: MIT License
Classifier: Operating System :: OS Independent
Requires-Python: >=3.0
License-File: LICENSE
Requires-Dist: telegram-util
Requires-Dist: pyyaml
Requires-Dist: webgram
Requires-Dist: telethon
